pinaxai/__init__.py
pinaxai/py.typed
pinaxai/docker/__init__.py
pinaxai/docker/api_client.py
pinaxai/docker/context.py
pinaxai/docker/resources.py
pinaxai/docker/app/__init__.py
pinaxai/docker/app/base.py
pinaxai/docker/app/celery/__init__.py
pinaxai/docker/app/celery/worker.py
pinaxai/docker/app/fastapi/__init__.py
pinaxai/docker/app/fastapi/fastapi.py
pinaxai/docker/app/postgres/__init__.py
pinaxai/docker/app/postgres/pgvector.py
pinaxai/docker/app/postgres/postgres.py
pinaxai/docker/app/redis/__init__.py
pinaxai/docker/app/redis/redis.py
pinaxai/docker/app/streamlit/__init__.py
pinaxai/docker/app/streamlit/streamlit.py
pinaxai/docker/app/whoami/__init__.py
pinaxai/docker/app/whoami/whoami.py
pinaxai/docker/resource/__init__.py
pinaxai/docker/resource/base.py
pinaxai/docker/resource/container.py
pinaxai/docker/resource/image.py
pinaxai/docker/resource/network.py
pinaxai/docker/resource/types.py
pinaxai/docker/resource/volume.py
pinaxai_docker-0.0.1.dist-info/METADATA
pinaxai_docker-0.0.1.dist-info/WHEEL
pinaxai_docker-0.0.1.dist-info/top_level.txt
pinaxai_docker-0.0.1.dist-info/RECORD
